Metadata-Version: 1.0
Name: userv.socket-server
Version: 0.3.0
Summary: Async server for userv
Home-page: https://github.com/SvenMatzke/userv
Author: SvenMatzke
Author-email: matzke.sven@googlemail.com
License: MIT
Platform: UNKNOWN
